{
    "KPlugin": {
        "Description": "Fade Effect",
        "Description[bg]": "Ефект на избледняване",
        "Description[bs]": "Efekt Izbljeđivanja",
        "Description[ca@valencia]": "Efecte d'esvaïment",
        "Description[ca]": "Efecte d'esvaïment",
        "Description[cs]": "Efekt mizení",
        "Description[da]": "Udtoningseffekt",
        "Description[de]": "Verblassungseffekt",
        "Description[el]": "Εφέ εξασθένισης",
        "Description[en_GB]": "Fade Effect",
        "Description[eo]": "Dissolva Efekto",
        "Description[es]": "Efecto de desvanecimiento",
        "Description[et]": "Hääbumisefekt",
        "Description[eu]": "Iraungitze-efektua",
        "Description[fi]": "Häivytystehoste",
        "Description[fr]": "Effet de fondu",
        "Description[gl]": "Efecto de esvaer.",
        "Description[hu]": "Elhalványodási effektus",
        "Description[it]": "Effetto di dissolvenza",
        "Description[ja]": "フェード効果",
        "Description[kk]": "Біртіндеу эффекті",
        "Description[ko]": "페이드 효과",
        "Description[mr]": "फिकटणे परिणाम",
        "Description[nb]": "Tone-effekt",
        "Description[nds]": "Utblennen",
        "Description[nl]": "Vervagingseffect",
        "Description[pl]": "Efekt zanikania",
        "Description[pt]": "Efeito de Desvanecimento",
        "Description[pt_BR]": "Efeito de desvanecimento",
        "Description[ru]": "Эффект затухания",
        "Description[sk]": "Efekt vytrácania",
        "Description[sl]": "Učinek pojemanja",
        "Description[sv]": "Toningseffekt",
        "Description[tr]": "Sönme Efekti",
        "Description[uk]": "Ефект згасання",
        "Description[wa]": "Efet di fondou",
        "Description[x-test]": "xxFade Effectxx",
        "Description[zh_TW]": "淡出效果",
        "Id": "kpr_pageeffect_fade",
        "Name": "Fade",
        "Name[bg]": "Избледняване",
        "Name[bs]": "Izblijediti",
        "Name[ca@valencia]": "Esvaïment",
        "Name[ca]": "Esvaïment",
        "Name[cs]": "Blednutí",
        "Name[da]": "Udtoning",
        "Name[de]": "Verblassen",
        "Name[el]": "Εξασθένιση",
        "Name[en_GB]": "Fade",
        "Name[eo]": "Dissolvi",
        "Name[es]": "Desvanecer",
        "Name[et]": "Hääbumine",
        "Name[eu]": "Iraungitzea",
        "Name[fi]": "Häivytys",
        "Name[fr]": "Estomper",
        "Name[ga]": "Céimnigh",
        "Name[gl]": "Esvaer",
        "Name[hu]": "Elhalványodás",
        "Name[ia]": "Pallidi",
        "Name[it]": "Dissolvi",
        "Name[ka]": "მინავლება",
        "Name[kk]": "Біртіндеу",
        "Name[ko]": "페이드",
        "Name[mr]": "फिकटणे",
        "Name[nb]": "Ton ut",
        "Name[nds]": "Utblennen",
        "Name[nl]": "Vervagen",
        "Name[nn]": "Ton inn og ut",
        "Name[pl]": "Zanikanie",
        "Name[pt]": "Desvanecer",
        "Name[pt_BR]": "Desvanecer",
        "Name[ru]": "Затухание",
        "Name[sk]": "Blednutie",
        "Name[sl]": "Pojemanje",
        "Name[sv]": "Tona",
        "Name[tr]": "Soldurmak",
        "Name[ug]": "سۇسلاشتۇر",
        "Name[uk]": "Згасання",
        "Name[wa]": "Fondou",
        "Name[x-test]": "xxFadexx",
        "Name[zh_CN]": "淡入",
        "Name[zh_TW]": "淡出",
        "ServiceTypes": [
            "CalligraStage/PageEffect"
        ]
    },
    "X-KPresenter-Version": "28"
}
