{
    "KPlugin": {
        "Name": "Plugin Shape",
        "Name[ca@valencia]": "Forma de connector",
        "Name[ca]": "Forma de connector",
        "Name[cs]": "Tvar modulu",
        "Name[en_GB]": "Plugin Shape",
        "Name[eo]": "Kromprograma Formo",
        "Name[es]": "Forma de complemento",
        "Name[eu]": "Plugin-forma",
        "Name[fr]": "Forme de prise",
        "Name[gl]": "Obxecto de complemento",
        "Name[it]": "Forma di estensione",
        "Name[ka]": "დამატების ფორმა",
        "Name[lv]": "Spraudņu objekts",
        "Name[nl]": "Plug-in voor vorm",
        "Name[pl]": "Kształt wtyczki",
        "Name[sl]": "Oblika vtičnika",
        "Name[sv]": "Insticksform",
        "Name[tr]": "Eklenti Şekli",
        "Name[uk]": "Форма додатка",
        "Name[x-test]": "xxPlugin Shapexx",
        "Name[zh_TW]": "外掛程式元件 ",
        "ServiceTypes": [
            "Calligra/Shape"
        ]
    },
    "X-Flake-MinVersion": "28",
    "X-Flake-PluginVersion": "28"
}
